{
    "url": "https://cellphones.com.vn/meizu-20-pro.html",
    "name": "Meizu 20 Pro",
    "price": "Giá Liên Hệ",
    "specifications": [
        {
            "category": "Màn hình",
            "details": {
                "Kích thước màn hình": "6.81 inches",
                "Công nghệ màn hình": "LTPO OLED",
                "Độ phân giải màn hình": "1440 x 3200 pixels (QHD+)",
                "Tính năng màn hình": "Tần số quét 120Hz, HDR10+, 500 nits"
            }
        },
        {
            "category": "Camera sau",
            "details": {
                "Camera sau": [
                    "Camera góc rộng: 50 MP, f/1.9, PDAF, OIS",
                    "Camera góc siêu rộng: 50 MP, f/2.2, 129˚",
                    "Camera Tele: 50 MP f/1.9, PDAF, optical zoom"
                ],
                "Quay video": "8K, 4K, 1080p; gyro-EIS",
                "Tính năng camera": "Đèn flash LED vòng, toàn cảnh, HDR"
            }
        },
        {
            "category": "Camera trước",
            "details": {
                "Camera trước": "Camera góc rộng: 32 MP, f/2.5"
            }
        },
        {
            "category": "Vi xử lý & đồ họa",
            "details": {
                "Chipset": "Snapdragon 8 Gen 2 (4 nm)",
                "GPU": "Adreno 740"
            }
        },
        {
            "category": "Giao tiếp & kết nối",
            "details": {
                "Công nghệ NFC": "Có",
                "Thẻ SIM": "2 SIM (Nano-SIM)",
                "Hồng ngoại": "Có",
                "Jack tai nghe 3.5": "Không",
                "Hỗ trợ mạng": "5G",
                "GPS": "GPS (L1+L5), GLONASS, BDS (B1I+B1c+B2a), GALILEO, QZSS"
            }
        },
        {
            "category": "RAM & lưu trữ",
            "details": {
                "Dung lượng RAM": "12 GB",
                "Bộ nhớ trong": "128 GB",
                "Khe cắm thẻ nhớ": "Không"
            }
        },
        {
            "category": "Pin & công nghệ sạc",
            "details": {
                "Pin": "5000 mAh",
                "Công nghệ sạc": "Sạc nhanh 80W",
                "Cổng sạc": "USB Type-C"
            }
        },
        {
            "category": "Tính năng khác",
            "details": {
                "Hệ điều hành": "Flyme 10"
            }
        },
        {
            "category": "Bộ xử lý & Đồ họa",
            "details": {
                "Loại CPU": "1x3.2 GHz Cortex-X3 & 2x2.8 GHz Cortex-A715 & 2x2.8 GHz Cortex-A710 & 3x2.0 GHz Cortex-A510"
            }
        },
        {
            "category": "Kích thước & Trọng lượng",
            "details": {
                "Kích thước": "164.2 x 76.4 x 7.8 mm",
                "Trọng lượng": "209 g"
            }
        },
        {
            "category": "Thông số khác",
            "details": {
                "Chỉ số kháng nước, bụi": "IP54",
                "Công nghệ âm thanh": "Stereo speakers"
            }
        },
        {
            "category": "Tiện ích khác",
            "details": {
                "Cảm biến vân tay": "Cảm biến vân tay trong màn hình",
                "Các loại cảm biến": "Cảm biến gia tốc, Cảm biến tiệm cận, La bàn, Con quay hồi chuyển, Cảm biến áp kế"
            }
        },
        {
            "category": "Cổng kết nối",
            "details": {
                "Wi-Fi": "802.11 а/b/g/n/ac/6e/7",
                "Bluetooth": "v5.3, A2DP, LE"
            }
        },
        {
            "category": "Thông tin chung",
            "details": {
                "Thời điểm ra mắt": "3/2023"
            }
        }
    ]
}