{
    "url": "https://mobilecity.vn/dien-thoai/realme-p2-pro-5g-sac-sieu-nhanh-80w.html",
    "name": "Realme P2 Pro 5G (sạc siêu nhanh 80W)",
    "price": "4850000",
    "specifications": [
        {
            "category": "Thông tin chung",
            "details": {
                "Hệ điều hành": "Android 14, Realme UI 5.0",
                "Ngôn ngữ": "Tiếng Việt, Đa ngôn ngữ"
            }
        },
        {
            "category": "Màn hình",
            "details": {
                "Loại màn hình": "OLED",
                "Màu màn hình": "1 tỷ màu",
                "Chuẩn màn hình": [
                    "OLED, 1 tỷ màu, 120Hz, 600 nits (typ), 1200 nits (HBM), 2000 nits (peak)",
                    "6.7 inches, Full HD+ (1080 x 2412 pixels)",
                    "Tỷ lệ 20:9; mật độ điểm ảnh ~394 ppi"
                ],
                "Độ phân giải": "1080 x 2412 pixels",
                "Màn hình rộng": "6.7 inches",
                "Công nghệ cảm ứng": "Cảm ứng điện dung đa điểm"
            }
        },
        {
            "category": "Chụp hình & Quay phim",
            "details": {
                "Camera sau": [
                    "50 MP f/1.9, 26mm (góc rộng), 1/1.95\", PDAF, OIS",
                    "8 MP, f/2.2, 16mm, 112˚(góc siêu rộng)",
                    "Quay phim: 4K@30fps, 1080p@30/60/120fps, gyro-EIS, OIS"
                ],
                "Camera trước": [
                    "32 MP, f/2.5, 21mm (góc rộng)",
                    "Quay phim: 4K@30fps, 1080p@30fps"
                ],
                "Đèn Flash": "Có",
                "Tính năng camera": "LED flash, HDR, panorama",
                "Quay phim": "4K@30fps, 1080p@30/60/120fps, gyro-EIS, OIS",
                "Videocall": "Có"
            }
        },
        {
            "category": "CPU & RAM",
            "details": {
                "Tốc độ CPU": [
                    "4x2.40 GHz Cortex-A78",
                    "4x1.95 GHz Cortex-A55"
                ],
                "Số nhân": "8 nhân",
                "Chipset": [
                    "Qualcomm SM7435-AB Snapdragon 7s Gen 2 (4 nm)",
                    "8 nhân (4x2.40 GHz & 4x1.95 GHz)",
                    "GPU: Adreno 710"
                ],
                "RAM": "8-12GB",
                "Chip đồ họa (GPU)": "Adreno 710"
            }
        },
        {
            "category": "Bộ nhớ & Lưu trữ",
            "details": {
                "Danh bạ": "Không giới hạn",
                "Bộ nhớ trong (ROM)": "128-512GB",
                "Thẻ nhớ ngoài": "Không"
            }
        },
        {
            "category": "Thiết kế & Trọng lượng",
            "details": {
                "Kiểu dáng": [
                    "Khung nhựa bo cong",
                    "Mặt lưng bo cong",
                    "Màn hình cong bằng kính cường lực",
                    "Kháng nước, bụi IP65"
                ],
                "Kích thước": "161.3 x 73.9 x 8.2 mm",
                "Trọng lượng (g)": "180 g"
            }
        },
        {
            "category": "Thông tin pin",
            "details": {
                "Dung lượng pin": [
                    "5200 mAh",
                    "Sạc nhanh 80W",
                    "Sạc 50% trong 19 ph, 100% trong 49 ph (QC)"
                ],
                "Pin có thể tháo rời": "Không"
            }
        },
        {
            "category": "Kết nối & Cổng giao tiếp",
            "details": {
                "3G": "HSDPA 850 / 900 / 2100",
                "4G": "HSPA, LTE, 5G",
                "Loại Sim": "2 SIM, Nano SIM",
                "Khe gắn Sim": "2 SIM, Nano SIM",
                "Wifi": "Wi-Fi 802.11 a/b/g/n/ac/6, băng tần kép",
                "GPS": "GPS, GLONASS, GALILEO, BDS, QZSS",
                "Bluetooth": "5.2, A2DP, LE",
                "GPRS/EDGE": "Có",
                "Jack tai nghe": [
                    "Không",
                    "Loa kép stereo"
                ],
                "NFC": "Không",
                "Kết nối USB": "USB Type-C 2.0",
                "Kết nối khác": "Không",
                "Cổng sạc": "Type-C"
            }
        },
        {
            "category": "Giải trí & Ứng dụng",
            "details": {
                "Cổng sạc": "Type-C",
                "Ghi âm": "Có",
                "FM radio": "Có"
            }
        }
    ]
}