{
    "url": "https://mobilecity.vn/dien-thoai/sony-xperia-1-iv.html",
    "name": "Sony Xperia 1 IV (1 Mark 4) 5G (Snapdragon 8 Gen 1, màn 4K)",
    "price": "19950000",
    "specifications": [
        {
            "category": "Thông tin chung",
            "details": {
                "Hệ điều hành": "Android 12",
                "Ngôn ngữ": "Tiếng Việt, Đa ngôn ngữ"
            }
        },
        {
            "category": "Màn hình",
            "details": {
                "Loại màn hình": "OLED",
                "Màu màn hình": "1 tỷ màu",
                "Chuẩn màn hình": [
                    "OLED, 1 tỷ màu, 120Hz, HDR BT.2020",
                    "6.5 inches, 4K+ (1644 x 3840 pixels), tỷ lệ 21:9",
                    "Corning Gorilla Glass Victus",
                    "Bình thường chạy ở 1096 x 2560 pixels, chỉ chạy 4K+ với các ứng dụng hỗ trợ"
                ],
                "Độ phân giải": "1644 x 3840 pixels",
                "Màn hình rộng": "6.5",
                "Công nghệ cảm ứng": "Cảm ứng điện dung đa điểm"
            }
        },
        {
            "category": "Chụp hình & Quay phim",
            "details": {
                "Camera sau": [
                    "12 MP, f/1.7, 24mm (góc rộng), Dual Pixel PDAF, OIS",
                    "12 MP, f/2.3, 85mm (tele), Dual Pixel PDAF, zoom 3.5x-5.2x, OIS",
                    "12 MP, f/2.2, 124˚, 16mm (góc siêu rộng), Dual Pixel PDAF",
                    "0.3 MP, TOF 3D, (độ sâu)",
                    "Quay phim: 4K@24/25/30/60/120fps HDR, 1080p@30/60/120/240fps; 5-axis gyro-EIS, OIS"
                ],
                "Camera trước": [
                    "12 MP, f/2.0, 24mm (góc rộng)",
                    "Quay phim: 4K@30fps, 1080p@30fps, 5-axis gyro-EIS"
                ],
                "Đèn Flash": "Có",
                "Tính năng camera": "Zeiss optics, Zeiss T* lens coating, LED flash, panorama, HDR, eye tracking",
                "Quay phim": "4K@24/25/30/60/120fps HDR, 1080p@30/60/120/240fps; 5-axis gyro-EIS, OIS",
                "Videocall": "Có"
            }
        },
        {
            "category": "CPU & RAM",
            "details": {
                "Tốc độ CPU": "1x3.00 GHz & 3x2.50 GHz & 4x1.80 GHz",
                "Số nhân": "8 nhân",
                "Chipset": [
                    "Qualcomm SM8450 Snapdragon 8 Gen 1 (4 nm)",
                    "8 nhân (1x3.00 GHz & 3x2.50 GHz & 4x1.80 GHz)",
                    "GPU: Adreno 730"
                ],
                "RAM": "12GB",
                "Chip đồ họa (GPU)": "Adreno 730"
            }
        },
        {
            "category": "Bộ nhớ & Lưu trữ",
            "details": {
                "Danh bạ": "Không giới hạn",
                "Bộ nhớ trong (ROM)": "256-512GB, UFS 3.X",
                "Thẻ nhớ ngoài": "microSDXC",
                "Hỗ trợ thẻ tối đa": "1TB"
            }
        },
        {
            "category": "Thiết kế & Trọng lượng",
            "details": {
                "Kiểu dáng": "Khung kim loại + Mặt lưng kính",
                "Kích thước": "165 x 71 x 8.2 mm",
                "Trọng lượng (g)": "185 g"
            }
        },
        {
            "category": "Thông tin pin",
            "details": {
                "Loại pin": "Li-Po",
                "Dung lượng pin": [
                    "Li-Po 5000 mAh",
                    "Sạc nhanh 30W, 50% trong 30 ph (quảng cáo)"
                ],
                "Pin có thể tháo rời": "Không"
            }
        },
        {
            "category": "Kết nối & Cổng giao tiếp",
            "details": {
                "3G": "HSDPA 800 / 850 / 900 / 1700(AWS) / 1900 / 2100",
                "4G": [
                    "1, 2, 3, 4, 5, 7, 8, 12, 13, 17, 19, 20, 25, 26, 28, 29, 32, 34, 38, 39, 40, 41, 46, 66 - Europe",
                    "1, 2, 3, 4, 5, 7, 8, 12, 13, 17, 19, 20, 25, 26, 28, 29, 32, 34, 38, 39, 40, 41, 46, 48, 66, 71 - USA",
                    "1, 2, 3, 4, 5, 7, 8, 12, 13, 17, 19, 20, 25, 26, 28, 29, 34, 38, 39, 40, 41, 46, 66 - Asia"
                ],
                "Loại Sim": "Nano-SIM hoặc eSIM",
                "Khe gắn Sim": [
                    "SIM đơn (Nano-SIM/eSIM) hoặc",
                    "SIM kép kết hợp (Nano-SIM, chế độ chờ kép)"
                ],
                "Wifi": "Wi-Fi 802.11 a/b/g/n/ac/6e, dual-band, Wi-Fi Direct, DLNA, hotspot",
                "GPS": "dual-band A-GPS, GLONASS, BDS, GALILEO, QZSS",
                "Bluetooth": "5.2, A2DP, LE Audio, aptX HD, aptX Adaptive",
                "GPRS/EDGE": "Có",
                "Jack tai nghe": "3.5 mm",
                "NFC": "Có",
                "Kết nối USB": "USB Type-C 3.2",
                "Kết nối khác": "NFC",
                "Cổng sạc": "Type-C"
            }
        },
        {
            "category": "Giải trí & Ứng dụng",
            "details": {
                "Xem phim": "Có",
                "Nghe nhạc": "Có",
                "Cổng sạc": "Type-C",
                "Ghi âm": "Có",
                "FM radio": "Có"
            }
        }
    ]
}