{
    "url": "https://cellphones.com.vn/xiaomi-poco-m4-pro.html",
    "name": "Xiaomi Poco M4 Pro",
    "price": "Giá Liên Hệ",
    "specifications": [
        {
            "category": "Màn hình",
            "details": {
                "Kích thước màn hình": "6.5 inches",
                "Công nghệ màn hình": "AMOLED",
                "Độ phân giải màn hình": "1080 x 2400 pixels (FullHD+)"
            }
        },
        {
            "category": "Camera sau",
            "details": {
                "Camera sau": [
                    "Camera rộng: 64 MP, f/1.8, PDAF",
                    "Camera góc siêu rộng: 8 MP, f/2.2, 118˚",
                    "Camera macrro: 2 MP, f/2.4"
                ],
                "Quay video": "1080p@30fps, 720p@30fps"
            }
        },
        {
            "category": "Camera trước",
            "details": {
                "Camera trước": "16MP, /2.4",
                "Quay video trước": "1080p@30fps"
            }
        },
        {
            "category": "Vi xử lý & đồ họa",
            "details": {
                "Chipset": "MediaTek Helio G96",
                "GPU": "Mali-G57 MC2"
            }
        },
        {
            "category": "Giao tiếp & kết nối",
            "details": {
                "Công nghệ NFC": "Có",
                "Thẻ SIM": "2 SIM (Nano-SIM)",
                "Jack tai nghe 3.5": "Không",
                "Hỗ trợ mạng": "4G",
                "GPS": "A-GPS, GLONASS, BDS, GALILEO"
            }
        },
        {
            "category": "RAM & lưu trữ",
            "details": {
                "Dung lượng RAM": "6 GB",
                "Bộ nhớ trong": "128 GB"
            }
        },
        {
            "category": "Pin & công nghệ sạc",
            "details": {
                "Pin": "5000mAh",
                "Công nghệ sạc": "Sạc nhanh 33W",
                "Cổng sạc": "USB Type-C"
            }
        },
        {
            "category": "Tính năng khác",
            "details": {
                "Hệ điều hành": "MIUI 13, Android 11"
            }
        },
        {
            "category": "Bộ xử lý & Đồ họa",
            "details": {
                "Loại CPU": "Octa-core CPU, up to 2.05GHz"
            }
        },
        {
            "category": "Kích thước & Trọng lượng",
            "details": {
                "Kích thước": "159.9 x 73.9 x 8.1 mm",
                "Trọng lượng": "179.5g"
            }
        },
        {
            "category": "Tiện ích khác",
            "details": {
                "Cảm biến vân tay": "Cảm biến vân tay cạnh bên",
                "Các loại cảm biến": "Cảm biến gia tốc, Cảm biến tiệm cận, Cảm biến ánh sáng, La bàn, Con quay hồi chuyển"
            }
        },
        {
            "category": "Cổng kết nối",
            "details": {
                "Wi-Fi": "Wi-Fi 802.11 a/b/g/n/ac, dual-band, Wi-Fi Direct, hotspot",
                "Bluetooth": "5.0"
            }
        }
    ]
}