{
    "url": "https://mobilecity.vn/dien-thoai/xiaomi-black-shark-5-china-aerospace-edition.html",
    "name": "Xiaomi Black Shark 5 China Aerospace Edition",
    "price": "12950000",
    "specifications": [
        {
            "category": "Thông tin chung",
            "details": {
                "Hệ điều hành": "Android 12, Joy UI 13",
                "Ngôn ngữ": "Đa ngôn ngữ"
            }
        },
        {
            "category": "Màn hình",
            "details": {
                "Loại màn hình": "AMOLED",
                "Màu màn hình": "16 triệu màu",
                "Chuẩn màn hình": [
                    "AMOLED, 144Hz",
                    "6.67 inches, Full HD+ (1080 x 2400 pixels)"
                ],
                "Độ phân giải": "1080 x 2400 pixels",
                "Màn hình rộng": "6.67 inches",
                "Công nghệ cảm ứng": "Cảm ứng điện dung đa điểm"
            }
        },
        {
            "category": "Chụp hình & Quay phim",
            "details": {
                "Camera sau": [
                    "64 MP, f/1.8, (góc rộng), PDAF",
                    "13 MP, f/2.4, 120˚ (góc siêu rộng)",
                    "2 MP, f/2.4, (macro)",
                    "Quay phim: 4K@30/60fps, 1080p@30/60/240fps, 1080p@960fps"
                ],
                "Camera trước": [
                    "16 MP, (góc rộng)",
                    "Quay phim: 1080p@30fps"
                ],
                "Đèn Flash": "Có",
                "Tính năng camera": "LED flash, HDR, panorama",
                "Quay phim": "4K@30/60fps, 1080p@30/60/240fps, 1080p@960fps",
                "Videocall": "Có"
            }
        },
        {
            "category": "CPU & RAM",
            "details": {
                "Tốc độ CPU": "1x3.2 GHz & 3x2.42 GHz & 4x1.80 GHz",
                "Số nhân": "8 nhân",
                "Chipset": [
                    "Qualcomm SM8250-AC Snapdragon 870 5G (7 nm)",
                    "8 nhân (1x3.2 GHz & 3x2.42 GHz & 4x1.80 GHz)",
                    "GPU: Adreno 650"
                ],
                "RAM": "12GB",
                "Chip đồ họa (GPU)": "Adreno 650"
            }
        },
        {
            "category": "Bộ nhớ & Lưu trữ",
            "details": {
                "Danh bạ": "Không giới hạn",
                "Bộ nhớ trong (ROM)": "256GB",
                "Thẻ nhớ ngoài": "Không"
            }
        },
        {
            "category": "Thiết kế & Trọng lượng",
            "details": {
                "Kiểu dáng": "Gaming phone",
                "Kích thước": "163.8 x 76.3 x 10 mm",
                "Trọng lượng (g)": "218 g"
            }
        },
        {
            "category": "Thông tin pin",
            "details": {
                "Loại pin": "Li-Po",
                "Dung lượng pin": [
                    "Li-Po 4650 mAh",
                    "Sạc nhanh 120W, 100% trong 15 phút (Quảng cáo)"
                ],
                "Pin có thể tháo rời": "Không"
            }
        },
        {
            "category": "Kết nối & Cổng giao tiếp",
            "details": {
                "3G": "HSDPA 800 / 850 / 900 / 1700(AWS) / 1900 / 2100",
                "4G": "1, 2, 3, 4, 5, 8, 18, 19, 26, 28, 34, 38, 39, 40, 41",
                "Loại Sim": "2 SIM, Nano SIM",
                "Khe gắn Sim": "2 SIM, Nano SIM",
                "Wifi": "Wi-Fi 802.11 a/b/g/n/ac/6, dual-band, Wi-Fi Direct, hotspot",
                "GPS": "A-GPS, GLONASS, GALILEO, QZSS, BDS",
                "Bluetooth": "5.2, A2DP, LE, aptX HD, aptX Adaptive",
                "GPRS/EDGE": "Có",
                "NFC": "Có",
                "Kết nối USB": "USB Type-C 2.0",
                "Kết nối khác": "NFC",
                "Cổng sạc": "Type-C 2.0"
            }
        },
        {
            "category": "Giải trí & Ứng dụng",
            "details": {
                "Cổng sạc": "Type-C 2.0",
                "Ghi âm": "Có",
                "FM radio": "Có"
            }
        }
    ]
}